dictionary/__init__.py
dictionary/dictionary.py
semih_demir_cs453_hw1-2.0.0.dist-info/METADATA
semih_demir_cs453_hw1-2.0.0.dist-info/WHEEL
semih_demir_cs453_hw1-2.0.0.dist-info/top_level.txt
semih_demir_cs453_hw1-2.0.0.dist-info/RECORD
